NshellFinder/__init__.py
NshellFinder/concat.py
NshellFinder/shell_information.py
NshellFinder-0.0.5.dist-info/METADATA
NshellFinder-0.0.5.dist-info/WHEEL
NshellFinder-0.0.5.dist-info/entry_points.txt
NshellFinder-0.0.5.dist-info/top_level.txt
NshellFinder-0.0.5.dist-info/RECORD
