Metadata-Version: 2.1
Name: NshellFinder
Version: 0.0.5
Summary: OVITO Python modifier to find n-th shell nearest neighbors.
Author-email: Killian Sheriff <ksheriff@mit.edu>
Maintainer-email: Killian Sheriff <ksheriff@mit.edu>
License: MIT License
Project-URL: repository, https://github.com/killiansheriff/NshellFinder
Keywords: ovito,python-modifier
Requires-Python: >=3.7
Requires-Dist: ovito >=3.9.1
